{
	"configurations" : 
	[
		{
			"directories" : 
			[
				{
					"build" : ".",
					"jsonFile" : "directory-.-Debug-f5ebdc15457944623624.json",
					"minimumCMakeVersion" : 
					{
						"string" : "3.24"
					},
					"projectIndex" : 0,
					"source" : ".",
					"targetIndexes" : 
					[
						0,
						1
					]
				}
			],
			"name" : "Debug",
			"projects" : 
			[
				{
					"directoryIndexes" : 
					[
						0
					],
					"name" : "PROJ1",
					"targetIndexes" : 
					[
						0,
						1
					]
				}
			],
			"targets" : 
			[
				{
					"directoryIndex" : 0,
					"id" : "DATA_STRUCTURES::@6890427a1f51a3e7e1df",
					"jsonFile" : "target-DATA_STRUCTURES-Debug-9f8e6dd81ad79aa4c74c.json",
					"name" : "DATA_STRUCTURES",
					"projectIndex" : 0
				},
				{
					"directoryIndex" : 0,
					"id" : "PROJ1::@6890427a1f51a3e7e1df",
					"jsonFile" : "target-PROJ1-Debug-81a1af3ca2641024591a.json",
					"name" : "PROJ1",
					"projectIndex" : 0
				}
			]
		}
	],
	"kind" : "codemodel",
	"paths" : 
	{
		"build" : "/home/gpinto03/FEUP/2\u00ba Ano/2\u00ba Semestre/Desenho de Algoritmos/Proj1DA/cmake-build-debug",
		"source" : "/home/gpinto03/FEUP/2\u00ba Ano/2\u00ba Semestre/Desenho de Algoritmos/Proj1DA"
	},
	"version" : 
	{
		"major" : 2,
		"minor" : 4
	}
}
